nanonis_spm/NanonisClass.py
nanonis_spm/__init__.py
nanonis_spm_examples/Example_AutoApproach.py
nanonis_spm_examples/Example_BiasPulsesAtVariousZ.py
nanonis_spm_examples/Example_BiasSpectroscopy.py
nanonis_spm_examples/Example_BiasSpectroscopy_MultiSegment.py
nanonis_spm_examples/Example_Custom2DSweep_GenSweeper.py
nanonis_spm_examples/Example_CustomBiasSweep.py
nanonis_spm_examples/Example_CustomZSweep.py
nanonis_spm_examples/Example_ForceDistanceCurve_OffsetComp.py
nanonis_spm_examples/Example_GenSweeper_MultipleSweeps.py
nanonis_spm_examples/Example_LockInSweep.py
nanonis_spm_examples/Example_RFGen_FreqSweep.py
nanonis_spm_examples/Example_RFGen_FreqSweep_Triggered.py
nanonis_spm_examples/Example_RFGen_GenSweeper.py
nanonis_spm_examples/Example_ScansAtDifferentBias.py
nanonis_spm_examples/Example_SimpleSignalAcquisition.py
nanonis_spm_examples/Example_SwitchMode_STM_AFM.py
nanonis_spm_examples/Example_TipCleaner.py
nanonis_spm_examples/Example_TipShaper.py
nanonis_spm_examples/Example_ZDriftMeasurement.py
nanonis_spm-1.0.9.dist-info/METADATA
nanonis_spm-1.0.9.dist-info/WHEEL
nanonis_spm-1.0.9.dist-info/licenses/LICENSE
nanonis_spm-1.0.9.dist-info/RECORD
