Metadata-Version: 2.4
Name: nanonis_spm
Version: 1.0.9
Summary: Python package for controlling Nanonis SPM software through Python
Author-email: Samuel O'Neill <support@specs-zurich.com>
Maintainer-email: Aitziber Herrero <support@specs-zurich.com>
License-File: LICENSE
Classifier: Operating System :: OS Independent
Classifier: Programming Language :: Python :: 3
Requires-Python: >=3.8
